{"frames": [{"frame": {"h": 326,"w": 474,"x": 958,"y": 252},"rotated": false,"spriteSourceSize": {"h": 326,"w": 474,"x": 83,"y": 313}},{"frame": {"h": 326,"w": 474,"x": 958,"y": 252},"rotated": false,"spriteSourceSize": {"h": 326,"w": 474,"x": 83,"y": 313}},{"frame": {"h": 320,"w": 474,"x": 480,"y": 284},"rotated": false,"spriteSourceSize": {"h": 320,"w": 474,"x": 83,"y": 315}},{"frame": {"h": 280,"w": 476,"x": 480,"y": 2},"rotated": false,"spriteSourceSize": {"h": 280,"w": 476,"x": 84,"y": 325}},{"frame": {"h": 280,"w": 476,"x": 480,"y": 2},"rotated": false,"spriteSourceSize": {"h": 280,"w": 476,"x": 84,"y": 325}},{"frame": {"h": 306,"w": 474,"x": 2,"y": 316},"rotated": false,"spriteSourceSize": {"h": 306,"w": 474,"x": 86,"y": 315}},{"frame": {"h": 306,"w": 474,"x": 2,"y": 316},"rotated": false,"spriteSourceSize": {"h": 306,"w": 474,"x": 86,"y": 315}},{"frame": {"h": 324,"w": 472,"x": 2,"y": 624},"rotated": false,"spriteSourceSize": {"h": 324,"w": 472,"x": 88,"y": 311}},{"frame": {"h": 328,"w": 472,"x": 1434,"y": 330},"rotated": false,"spriteSourceSize": {"h": 328,"w": 472,"x": 88,"y": 310}},{"frame": {"h": 328,"w": 472,"x": 1434,"y": 330},"rotated": false,"spriteSourceSize": {"h": 328,"w": 472,"x": 88,"y": 310}},{"frame": {"h": 324,"w": 472,"x": 478,"y": 606},"rotated": false,"spriteSourceSize": {"h": 324,"w": 472,"x": 88,"y": 312}},{"frame": {"h": 324,"w": 472,"x": 478,"y": 606},"rotated": false,"spriteSourceSize": {"h": 324,"w": 472,"x": 88,"y": 312}},{"frame": {"h": 322,"w": 472,"x": 1430,"y": 660},"rotated": false,"spriteSourceSize": {"h": 322,"w": 472,"x": 88,"y": 313}},{"frame": {"h": 322,"w": 472,"x": 1430,"y": 660},"rotated": false,"spriteSourceSize": {"h": 322,"w": 472,"x": 88,"y": 313}},{"frame": {"h": 322,"w": 472,"x": 1430,"y": 660},"rotated": false,"spriteSourceSize": {"h": 322,"w": 472,"x": 88,"y": 313}},{"frame": {"h": 322,"w": 472,"x": 1430,"y": 660},"rotated": false,"spriteSourceSize": {"h": 322,"w": 472,"x": 88,"y": 313}},{"frame": {"h": 322,"w": 472,"x": 1430,"y": 660},"rotated": false,"spriteSourceSize": {"h": 322,"w": 472,"x": 88,"y": 313}},{"frame": {"h": 322,"w": 472,"x": 1430,"y": 660},"rotated": false,"spriteSourceSize": {"h": 322,"w": 472,"x": 88,"y": 313}},{"frame": {"h": 322,"w": 472,"x": 1430,"y": 660},"rotated": false,"spriteSourceSize": {"h": 322,"w": 472,"x": 88,"y": 313}},{"frame": {"h": 322,"w": 472,"x": 1430,"y": 660},"rotated": false,"spriteSourceSize": {"h": 322,"w": 472,"x": 88,"y": 313}},{"frame": {"h": 322,"w": 472,"x": 1430,"y": 660},"rotated": false,"spriteSourceSize": {"h": 322,"w": 472,"x": 88,"y": 313}},{"frame": {"h": 322,"w": 472,"x": 1430,"y": 660},"rotated": false,"spriteSourceSize": {"h": 322,"w": 472,"x": 88,"y": 313}},{"frame": {"h": 322,"w": 472,"x": 1430,"y": 660},"rotated": false,"spriteSourceSize": {"h": 322,"w": 472,"x": 88,"y": 313}},{"frame": {"h": 322,"w": 472,"x": 1430,"y": 660},"rotated": false,"spriteSourceSize": {"h": 322,"w": 472,"x": 88,"y": 313}},{"frame": {"h": 322,"w": 472,"x": 1430,"y": 660},"rotated": false,"spriteSourceSize": {"h": 322,"w": 472,"x": 88,"y": 313}},{"frame": {"h": 322,"w": 472,"x": 1430,"y": 660},"rotated": false,"spriteSourceSize": {"h": 322,"w": 472,"x": 88,"y": 313}},{"frame": {"h": 322,"w": 472,"x": 1430,"y": 660},"rotated": false,"spriteSourceSize": {"h": 322,"w": 472,"x": 88,"y": 313}},{"frame": {"h": 322,"w": 472,"x": 1430,"y": 660},"rotated": false,"spriteSourceSize": {"h": 322,"w": 472,"x": 88,"y": 313}},{"frame": {"h": 322,"w": 472,"x": 1430,"y": 660},"rotated": false,"spriteSourceSize": {"h": 322,"w": 472,"x": 88,"y": 313}},{"frame": {"h": 322,"w": 472,"x": 1430,"y": 660},"rotated": false,"spriteSourceSize": {"h": 322,"w": 472,"x": 88,"y": 313}},{"frame": {"h": 322,"w": 472,"x": 1430,"y": 660},"rotated": false,"spriteSourceSize": {"h": 322,"w": 472,"x": 88,"y": 313}},{"frame": {"h": 322,"w": 472,"x": 1430,"y": 660},"rotated": false,"spriteSourceSize": {"h": 322,"w": 472,"x": 88,"y": 313}},{"frame": {"h": 322,"w": 472,"x": 1430,"y": 660},"rotated": false,"spriteSourceSize": {"h": 322,"w": 472,"x": 88,"y": 313}},{"frame": {"h": 322,"w": 472,"x": 1430,"y": 660},"rotated": false,"spriteSourceSize": {"h": 322,"w": 472,"x": 88,"y": 313}},{"frame": {"h": 322,"w": 472,"x": 1430,"y": 660},"rotated": false,"spriteSourceSize": {"h": 322,"w": 472,"x": 88,"y": 313}},{"frame": {"h": 322,"w": 472,"x": 1430,"y": 660},"rotated": false,"spriteSourceSize": {"h": 322,"w": 472,"x": 88,"y": 313}},{"frame": {"h": 322,"w": 472,"x": 1430,"y": 660},"rotated": false,"spriteSourceSize": {"h": 322,"w": 472,"x": 88,"y": 313}},{"frame": {"h": 322,"w": 472,"x": 1430,"y": 660},"rotated": false,"spriteSourceSize": {"h": 322,"w": 472,"x": 88,"y": 313}},{"frame": {"h": 322,"w": 472,"x": 1430,"y": 660},"rotated": false,"spriteSourceSize": {"h": 322,"w": 472,"x": 88,"y": 313}},{"frame": {"h": 322,"w": 472,"x": 1430,"y": 660},"rotated": false,"spriteSourceSize": {"h": 322,"w": 472,"x": 88,"y": 313}},{"frame": {"h": 322,"w": 472,"x": 1430,"y": 660},"rotated": false,"spriteSourceSize": {"h": 322,"w": 472,"x": 88,"y": 313}},{"frame": {"h": 322,"w": 472,"x": 1430,"y": 660},"rotated": false,"spriteSourceSize": {"h": 322,"w": 472,"x": 88,"y": 313}},{"frame": {"h": 322,"w": 472,"x": 1430,"y": 660},"rotated": false,"spriteSourceSize": {"h": 322,"w": 472,"x": 88,"y": 313}},{"frame": {"h": 322,"w": 472,"x": 1430,"y": 660},"rotated": false,"spriteSourceSize": {"h": 322,"w": 472,"x": 88,"y": 313}},{"frame": {"h": 322,"w": 472,"x": 1430,"y": 660},"rotated": false,"spriteSourceSize": {"h": 322,"w": 472,"x": 88,"y": 313}},{"frame": {"h": 322,"w": 472,"x": 1430,"y": 660},"rotated": false,"spriteSourceSize": {"h": 322,"w": 472,"x": 88,"y": 313}},{"frame": {"h": 322,"w": 472,"x": 1430,"y": 660},"rotated": false,"spriteSourceSize": {"h": 322,"w": 472,"x": 88,"y": 313}},{"frame": {"h": 322,"w": 472,"x": 1430,"y": 660},"rotated": false,"spriteSourceSize": {"h": 322,"w": 472,"x": 88,"y": 313}},{"frame": {"h": 322,"w": 472,"x": 1430,"y": 660},"rotated": false,"spriteSourceSize": {"h": 322,"w": 472,"x": 88,"y": 313}},{"frame": {"h": 322,"w": 472,"x": 1430,"y": 660},"rotated": false,"spriteSourceSize": {"h": 322,"w": 472,"x": 88,"y": 313}},{"frame": {"h": 322,"w": 472,"x": 1430,"y": 660},"rotated": false,"spriteSourceSize": {"h": 322,"w": 472,"x": 88,"y": 313}},{"frame": {"h": 322,"w": 472,"x": 1430,"y": 660},"rotated": false,"spriteSourceSize": {"h": 322,"w": 472,"x": 88,"y": 313}},{"frame": {"h": 322,"w": 472,"x": 1430,"y": 660},"rotated": false,"spriteSourceSize": {"h": 322,"w": 472,"x": 88,"y": 313}},{"frame": {"h": 322,"w": 472,"x": 1430,"y": 660},"rotated": false,"spriteSourceSize": {"h": 322,"w": 472,"x": 88,"y": 313}},{"frame": {"h": 322,"w": 472,"x": 1430,"y": 660},"rotated": false,"spriteSourceSize": {"h": 322,"w": 472,"x": 88,"y": 313}},{"frame": {"h": 322,"w": 472,"x": 1430,"y": 660},"rotated": false,"spriteSourceSize": {"h": 322,"w": 472,"x": 88,"y": 313}},{"frame": {"h": 322,"w": 472,"x": 1430,"y": 660},"rotated": false,"spriteSourceSize": {"h": 322,"w": 472,"x": 88,"y": 313}},{"frame": {"h": 322,"w": 472,"x": 1430,"y": 660},"rotated": false,"spriteSourceSize": {"h": 322,"w": 472,"x": 88,"y": 313}},{"frame": {"h": 322,"w": 472,"x": 1430,"y": 660},"rotated": false,"spriteSourceSize": {"h": 322,"w": 472,"x": 88,"y": 313}},{"frame": {"h": 322,"w": 472,"x": 1430,"y": 660},"rotated": false,"spriteSourceSize": {"h": 322,"w": 472,"x": 88,"y": 313}},{"frame": {"h": 322,"w": 472,"x": 1430,"y": 660},"rotated": false,"spriteSourceSize": {"h": 322,"w": 472,"x": 88,"y": 313}},{"frame": {"h": 322,"w": 472,"x": 1430,"y": 660},"rotated": false,"spriteSourceSize": {"h": 322,"w": 472,"x": 88,"y": 313}},{"frame": {"h": 322,"w": 472,"x": 1430,"y": 660},"rotated": false,"spriteSourceSize": {"h": 322,"w": 472,"x": 88,"y": 313}},{"frame": {"h": 322,"w": 472,"x": 1430,"y": 660},"rotated": false,"spriteSourceSize": {"h": 322,"w": 472,"x": 88,"y": 313}},{"frame": {"h": 322,"w": 472,"x": 1430,"y": 660},"rotated": false,"spriteSourceSize": {"h": 322,"w": 472,"x": 88,"y": 313}},{"frame": {"h": 322,"w": 472,"x": 1430,"y": 660},"rotated": false,"spriteSourceSize": {"h": 322,"w": 472,"x": 88,"y": 313}},{"frame": {"h": 322,"w": 472,"x": 1430,"y": 660},"rotated": false,"spriteSourceSize": {"h": 322,"w": 472,"x": 88,"y": 313}},{"frame": {"h": 322,"w": 472,"x": 1430,"y": 660},"rotated": false,"spriteSourceSize": {"h": 322,"w": 472,"x": 88,"y": 313}},{"frame": {"h": 322,"w": 472,"x": 1430,"y": 660},"rotated": false,"spriteSourceSize": {"h": 322,"w": 472,"x": 88,"y": 313}},{"frame": {"h": 322,"w": 472,"x": 1430,"y": 660},"rotated": false,"spriteSourceSize": {"h": 322,"w": 472,"x": 88,"y": 313}},{"frame": {"h": 322,"w": 472,"x": 1430,"y": 660},"rotated": false,"spriteSourceSize": {"h": 322,"w": 472,"x": 88,"y": 313}},{"frame": {"h": 322,"w": 472,"x": 1430,"y": 660},"rotated": false,"spriteSourceSize": {"h": 322,"w": 472,"x": 88,"y": 313}},{"frame": {"h": 322,"w": 472,"x": 1430,"y": 660},"rotated": false,"spriteSourceSize": {"h": 322,"w": 472,"x": 88,"y": 313}},{"frame": {"h": 322,"w": 472,"x": 1430,"y": 660},"rotated": false,"spriteSourceSize": {"h": 322,"w": 472,"x": 88,"y": 313}},{"frame": {"h": 322,"w": 472,"x": 1430,"y": 660},"rotated": false,"spriteSourceSize": {"h": 322,"w": 472,"x": 88,"y": 313}},{"frame": {"h": 322,"w": 472,"x": 1430,"y": 660},"rotated": false,"spriteSourceSize": {"h": 322,"w": 472,"x": 88,"y": 313}},{"frame": {"h": 322,"w": 472,"x": 1430,"y": 660},"rotated": false,"spriteSourceSize": {"h": 322,"w": 472,"x": 88,"y": 313}},{"frame": {"h": 322,"w": 472,"x": 1430,"y": 660},"rotated": false,"spriteSourceSize": {"h": 322,"w": 472,"x": 88,"y": 313}},{"frame": {"h": 322,"w": 472,"x": 1430,"y": 660},"rotated": false,"spriteSourceSize": {"h": 322,"w": 472,"x": 88,"y": 313}},{"frame": {"h": 322,"w": 472,"x": 1430,"y": 660},"rotated": false,"spriteSourceSize": {"h": 322,"w": 472,"x": 88,"y": 313}},{"frame": {"h": 322,"w": 472,"x": 1430,"y": 660},"rotated": false,"spriteSourceSize": {"h": 322,"w": 472,"x": 88,"y": 313}},{"frame": {"h": 324,"w": 472,"x": 956,"y": 580},"rotated": false,"spriteSourceSize": {"h": 324,"w": 472,"x": 88,"y": 314}},{"frame": {"h": 248,"w": 476,"x": 958,"y": 2},"rotated": false,"spriteSourceSize": {"h": 248,"w": 476,"x": 83,"y": 388}},{"frame": {"h": 248,"w": 476,"x": 958,"y": 2},"rotated": false,"spriteSourceSize": {"h": 248,"w": 476,"x": 83,"y": 388}},{"frame": {"h": 106,"w": 458,"x": 1912,"y": 2},"rotated": true,"spriteSourceSize": {"h": 106,"w": 458,"x": 92,"y": 531}},{"frame": {"h": 106,"w": 458,"x": 1912,"y": 2},"rotated": true,"spriteSourceSize": {"h": 106,"w": 458,"x": 92,"y": 531}},{"frame": {"h": 164,"w": 472,"x": 952,"y": 906},"rotated": false,"spriteSourceSize": {"h": 164,"w": 472,"x": 78,"y": 467}},{"frame": {"h": 164,"w": 472,"x": 952,"y": 906},"rotated": false,"spriteSourceSize": {"h": 164,"w": 472,"x": 78,"y": 467}},{"frame": {"h": 312,"w": 476,"x": 2,"y": 2},"rotated": false,"spriteSourceSize": {"h": 312,"w": 476,"x": 83,"y": 327}},{"frame": {"h": 326,"w": 474,"x": 1436,"y": 2},"rotated": false,"spriteSourceSize": {"h": 326,"w": 474,"x": 83,"y": 314}},{"frame": {"h": 326,"w": 474,"x": 958,"y": 252},"rotated": false,"spriteSourceSize": {"h": 326,"w": 474,"x": 83,"y": 313}},{"frame": {"h": 326,"w": 474,"x": 958,"y": 252},"rotated": false,"spriteSourceSize": {"h": 326,"w": 474,"x": 83,"y": 313}}],"meta": {"format": "RGBA4444","image": "Romo_Emotion_Curious_Idle.png","scale": "1","size": {"h": 2048,"w": 2048}}}